udtool/__init__.py
udtool/console.py
udtool-0.1.0.dist-info/entry_points.txt
udtool-0.1.0.dist-info/WHEEL
udtool-0.1.0.dist-info/METADATA
udtool-0.1.0.dist-info/RECORD
