Metadata-Version: 2.1
Name: udtool
Version: 0.1.0
Summary: A deploy tool for UnrealEngine
Author: Marc Seiler
Author-email: mseielr@crazyfacegames.com
Requires-Python: >=3.10,<4.0
Classifier: Programming Language :: Python :: 3
Classifier: Programming Language :: Python :: 3.10
Requires-Dist: requests (>=2.27.1,<3.0.0)
